setup.py
cuav/__init__.py
cuav.egg-info/PKG-INFO
cuav.egg-info/SOURCES.txt
cuav.egg-info/dependency_links.txt
cuav.egg-info/requires.txt
cuav.egg-info/top_level.txt
cuav.egg-info/zip-safe
cuav/camera/__init__.py
cuav/camera/cam_params.py
cuav/camera/findjoe.py
cuav/camera/reduce_depth.py
cuav/camera/undistort.py
cuav/data/ChameleonArecort/params.json
cuav/data/PiCamV2/params.json
cuav/data/PiCamV2/params_half.json
cuav/image/__init__.py
cuav/image/imageutil.c
cuav/image/scanner.c
cuav/image/include/imageutil.h
cuav/lib/__init__.py
cuav/lib/block_xmit.py
cuav/lib/cuav_command.py
cuav/lib/cuav_joe.py
cuav/lib/cuav_landingregion.py
cuav/lib/cuav_mosaic.py
cuav/lib/cuav_region.py
cuav/lib/cuav_slipmap.py
cuav/lib/cuav_util.py
cuav/lib/mav_position.py
cuav/lib/rotmat.py
cuav/modules/__init__.py
cuav/modules/camera_air.py
cuav/modules/camera_ground.py
cuav/modules/checklist.py
cuav/modules/cuav_check.py
cuav/modules/cuav_companion.py
cuav/modules/cuav_heli.py
cuav/modules/libchecklist.py
cuav/modules/nmea.py
cuav/tools/__init__.py
cuav/tools/agl_mission.py
cuav/tools/algtest.py
cuav/tools/calibrate.py
cuav/tools/cuav_benchmark.py
cuav/tools/cuav_lens.py
cuav/tools/cuav_missiongenerator.py
cuav/tools/geosearch.py
cuav/tools/geotag.py
cuav/tools/logbook.py
cuav/tools/playback.py
cuav/tools/playback_matchpos.py
cuav/tools/run_block_xmit.py
cuav/tools/scantest.py
cuav/tools/speedtest_cv.py
cuav/tools/thermal_view.py
cuav/uav/__init__.py
cuav/uav/euclid.py
cuav/uav/geo.py
cuav/uav/kml.py
cuav/uav/test.py
cuav/uav/uav.py