Metadata-Version: 1.1
Name: cuav
Version: 1.5.0
Summary: CanberraUAV UAV code
Home-page: https://github.com/CanberraUAV/cuav
Author: CanberraUAV
Author-email: andrew-cuav@tridgell.net
License: GPLv3
Platform: UNKNOWN
Classifier: Development Status :: 4 - Beta
Classifier: Environment :: Console
Classifier: Intended Audience :: Science/Research
Classifier: License :: OSI Approved :: GNU General Public License v3 (GPLv3)
Classifier: Operating System :: OS Independent
Classifier: Programming Language :: Python :: 2.7
Classifier: Topic :: Scientific/Engineering
